braincloud/_version.py
braincloud-0.2.2.dist-info/licenses/LICENSE-apache.txt
braincloud-0.2.2.dist-info/METADATA
braincloud-0.2.2.dist-info/WHEEL
braincloud-0.2.2.dist-info/top_level.txt
braincloud-0.2.2.dist-info/RECORD
